CHANGELOG
LICENSE
MANIFEST.in
README.rst
product.xml
setup.cfg
setup.py
./__init__.py
./i18n.py
./product.py
./product.xml
./tryton.cfg
./website.py
./i18n/messages.pot
./i18n/pt_BR/LC_MESSAGES/messages.po
./locale/de_DE.po
./view/nereid_website_product.xml
./view/product_form_nereid.xml
./view/product_media_form.xml
./view/product_media_tree.xml
./view/template_form.xml
locale/de_DE.po
tests/__init__.py
tests/test_catalog.py
tests/test_product.py
trytond_nereid_catalog.egg-info/PKG-INFO
trytond_nereid_catalog.egg-info/SOURCES.txt
trytond_nereid_catalog.egg-info/dependency_links.txt
trytond_nereid_catalog.egg-info/entry_points.txt
trytond_nereid_catalog.egg-info/not-zip-safe
trytond_nereid_catalog.egg-info/pbr.json
trytond_nereid_catalog.egg-info/requires.txt
trytond_nereid_catalog.egg-info/top_level.txt
view/nereid_website_product.xml
view/product_form_nereid.xml
view/product_media_form.xml
view/product_media_tree.xml
view/template_form.xml